MANIFEST.in
README.md
meta.json
setup.py
xx_swahili_spacy/__init__.py
xx_swahili_spacy/meta.json
xx_swahili_spacy.egg-info/PKG-INFO
xx_swahili_spacy.egg-info/SOURCES.txt
xx_swahili_spacy.egg-info/dependency_links.txt
xx_swahili_spacy.egg-info/entry_points.txt
xx_swahili_spacy.egg-info/not-zip-safe
xx_swahili_spacy.egg-info/requires.txt
xx_swahili_spacy.egg-info/top_level.txt
xx_swahili_spacy/xx_swahili_spacy-0.0.1/README.md
xx_swahili_spacy/xx_swahili_spacy-0.0.1/config.cfg
xx_swahili_spacy/xx_swahili_spacy-0.0.1/meta.json
xx_swahili_spacy/xx_swahili_spacy-0.0.1/tokenizer
xx_swahili_spacy/xx_swahili_spacy-0.0.1/ner/cfg
xx_swahili_spacy/xx_swahili_spacy-0.0.1/ner/model
xx_swahili_spacy/xx_swahili_spacy-0.0.1/ner/moves
xx_swahili_spacy/xx_swahili_spacy-0.0.1/tok2vec/cfg
xx_swahili_spacy/xx_swahili_spacy-0.0.1/tok2vec/model
xx_swahili_spacy/xx_swahili_spacy-0.0.1/vocab/key2row
xx_swahili_spacy/xx_swahili_spacy-0.0.1/vocab/lookups.bin
xx_swahili_spacy/xx_swahili_spacy-0.0.1/vocab/strings.json
xx_swahili_spacy/xx_swahili_spacy-0.0.1/vocab/vectors
xx_swahili_spacy/xx_swahili_spacy-0.0.1/vocab/vectors.cfg