Metadata-Version: 2.1
Name: xx-swahili-spacy
Version: 0.0.1
Summary: UNKNOWN
Home-page: UNKNOWN
Author: 
Author-email: 
License: UNKNOWN
Platform: UNKNOWN
